lazyuptimerobot/__init__.py
lazyuptimerobot/lazyuptimerobot.py
lazyuptimerobot/uptimerobot.py
lazyuptimerobot.py-2.0.0.dist-info/LICENSE
lazyuptimerobot.py-2.0.0.dist-info/METADATA
lazyuptimerobot.py-2.0.0.dist-info/WHEEL
lazyuptimerobot.py-2.0.0.dist-info/top_level.txt
lazyuptimerobot.py-2.0.0.dist-info/RECORD
